{
  "stock_selection_result": {
    "trade_week": "2026-W25",
    "theme_pool": [
      {
        "theme": "创新药",
        "source": "weekly_confirmed",
        "rank": 1,
        "reason_text": "来自 final_result. 的周级确认主线，创新药ETF与减肥药板块资金极致抱团"
      },
      {
        "theme": "半导体设备",
        "source": "weekly_confirmed",
        "rank": 2,
        "reason_text": "来自 final_result. 的周级确认主线，大基金持股与光刻机概念反复走强"
      },
      {
        "theme": "AI消费电子",
        "source": "weekly_confirmed",
        "rank": 3,
        "reason_text": "来自 final_result. 的周级确认主线，AI手机、AI PC与华为链爆发"
      },
      {
        "theme": "算力硬件",
        "source": "weekly_and_reference",
        "rank": 4,
        "reason_text": "来自 final_result. 的周级确认主线，CPO、PCB及铜连接与AI主线共振，且在reference中也有CPO/PCB印证"
      },
      {
        "theme": "氟化工",
        "source": "weekly_and_reference",
        "rank": 5,
        "reason_text": "来自 final_result. 的周级确认主线，受化工品利润回暖及供给收缩催化，reference中同样出现氟化工"
      },
      {
        "theme": "养殖",
        "source": "weekly_confirmed",
        "rank": 6,
        "reason_text": "来自 final_result. 的周级确认主线，猪肉与养鸡板块短期爆发，属防御性支线"
      }
    ],
    "candidate_stock_list": [
      {
        "stock_code": "002815",
        "stock_name": "崇达技术",
        "selection_score": 247,
        "matched_theme_list": [
          "算力硬件",
          "AI消费电子",
          "半导体设备",
          "PCB",
          "CPO",
          "先进封装"
        ],
        "matched_weekly_theme_list": [
          "算力硬件",
          "AI消费电子",
          "半导体设备"
        ],
        "matched_reference_theme_list": [
          "PCB",
          "CPO",
          "半导体",
          "AI",
          "PC",
          "6G"
        ],
        "matched_future_theme_list": [],
        "resonance_type": "strong",
        "industry_chain_path": [
          "AI服务器",
          "高速PCB",
          "IC载板"
        ],
        "business_relevance_label": "core_business_related",
        "noise_label_list": [
          "none"
        ],
        "reflection_risk_label_list": [
          "none"
        ],
        "holding_style_label": "main_theme_trend",
        "reason_text": "公司主营PCB，产品涵盖高多层板、HDI板等，直接受益于算力基建CPO与AI PC换机潮，同时布局IC载板切入半导体设备材料链，多主线强共振。",
        "risk_text": "若AI算力与消费电子换机需求不及预期，PCB产能扩张可能带来价格内卷风险。",
        "score_factor_signal": {
          "selection_score_config_version": "main_theme_v2_2026_06_29",
          "ranked_weekly_theme_hit_count": 2,
          "weekly_theme_hit_count": 3,
          "reference_theme_hit_count": 6,
          "future_theme_hit_count": 0,
          "related_sub_theme_hit_count": 1,
          "resonance_label": "strong",
          "resonance_score": 2,
          "business_relevance_label": "core_business_related",
          "business_relevance_score": 1,
          "noise_label_list": [
            "none"
          ],
          "noise_score": 0,
          "reflection_risk_label_list": [
            "none"
          ],
          "reflection_risk_score": 0
        }
      },
      {
        "stock_code": "000988",
        "stock_name": "华工科技",
        "selection_score": 245,
        "matched_theme_list": [
          "算力硬件",
          "半导体设备",
          "AI消费电子",
          "CPO",
          "光通信"
        ],
        "matched_weekly_theme_list": [
          "算力硬件",
          "半导体设备",
          "AI消费电子"
        ],
        "matched_reference_theme_list": [
          "光通信",
          "CPO",
          "半导体",
          "PCB",
          "AI",
          "6G",
          "存储半导体"
        ],
        "matched_future_theme_list": [],
        "resonance_type": "strong",
        "industry_chain_path": [
          "AI算力",
          "光通信/CPO",
          "光模块/光芯片",
          "消费电子传感"
        ],
        "business_relevance_label": "core_business_related",
        "noise_label_list": [
          "concept_stacking"
        ],
        "reflection_risk_label_list": [
          "none"
        ],
        "holding_style_label": "main_theme_trend",
        "reason_text": "公司光模块业务全球领先，主营光通信器件与传感器，精准命中算力硬件、半导体及AI消费电子多条主线，产业链路径极清晰，属于多主线强共振核心标的。",
        "risk_text": "概念标签极多，部分概念与主营关联弱；若科技主线整体退潮，高估值可能面临回调。",
        "score_factor_signal": {
          "selection_score_config_version": "main_theme_v2_2026_06_29",
          "ranked_weekly_theme_hit_count": 2,
          "weekly_theme_hit_count": 3,
          "reference_theme_hit_count": 7,
          "future_theme_hit_count": 0,
          "related_sub_theme_hit_count": 0,
          "resonance_label": "strong",
          "resonance_score": 2,
          "business_relevance_label": "core_business_related",
          "business_relevance_score": 1,
          "noise_label_list": [
            "concept_stacking"
          ],
          "noise_score": -1,
          "reflection_risk_label_list": [
            "none"
          ],
          "reflection_risk_score": 0
        }
      },
      {
        "stock_code": "603773",
        "stock_name": "沃格光电",
        "selection_score": 242,
        "matched_theme_list": [
          "半导体设备",
          "AI消费电子",
          "算力硬件",
          "CPO",
          "6G",
          "半导体",
          "玻璃基板",
          "存储半导体",
          "光通信"
        ],
        "matched_weekly_theme_list": [
          "半导体设备",
          "AI消费电子",
          "算力硬件"
        ],
        "matched_reference_theme_list": [
          "CPO",
          "6G",
          "半导体",
          "玻璃基板",
          "存储半导体",
          "光通信"
        ],
        "matched_future_theme_list": [],
        "resonance_type": "strong",
        "industry_chain_path": [
          "玻璃基板",
          "先进封装/CPO/MiniLED",
          "AI算力服务器/消费电子终端"
        ],
        "business_relevance_label": "core_business_related",
        "noise_label_list": [
          "none"
        ],
        "reflection_risk_label_list": [
          "none"
        ],
        "holding_style_label": "main_theme_trend",
        "reason_text": "公司主营玻璃基线路板，是半导体先进封装和CPO光模块的核心材料，产品直接切入AI算力服务器和新型显示终端，同时命中半导体、算力硬件和消费电子三大主线，产业链逻辑极硬。",
        "risk_text": "玻璃基板在先进封装和CPO领域的渗透率提升速度若不及预期，可能影响公司业绩释放。",
        "score_factor_signal": {
          "selection_score_config_version": "main_theme_v2_2026_06_29",
          "ranked_weekly_theme_hit_count": 2,
          "weekly_theme_hit_count": 3,
          "reference_theme_hit_count": 6,
          "future_theme_hit_count": 0,
          "related_sub_theme_hit_count": 0,
          "resonance_label": "strong",
          "resonance_score": 2,
          "business_relevance_label": "core_business_related",
          "business_relevance_score": 1,
          "noise_label_list": [
            "none"
          ],
          "noise_score": 0,
          "reflection_risk_label_list": [
            "none"
          ],
          "reflection_risk_score": 0
        }
      },
      {
        "stock_code": "000063",
        "stock_name": "中兴通讯",
        "selection_score": 226,
        "matched_theme_list": [
          "AI消费电子",
          "算力硬件",
          "半导体设备",
          "光通信",
          "6G",
          "AI应用"
        ],
        "matched_weekly_theme_list": [
          "AI消费电子",
          "算力硬件",
          "半导体设备"
        ],
        "matched_reference_theme_list": [
          "光通信",
          "6G",
          "AI应用",
          "AI",
          "PC"
        ],
        "matched_future_theme_list": [],
        "resonance_type": "strong",
        "industry_chain_path": [
          "AI手机终端",
          "算力服务器",
          "光通信网络",
          "芯片"
        ],
        "business_relevance_label": "core_business_related",
        "noise_label_list": [
          "none"
        ],
        "reflection_risk_label_list": [
          "none"
        ],
        "holding_style_label": "main_theme_trend",
        "reason_text": "公司主营通信设备和算力服务器，精准命中AI消费电子(AI手机)、算力硬件(AIDC/液冷)和半导体(芯片)三大前排主线，且与光通信等reference主题强共振，产业链路径极为清晰。",
        "risk_text": "作为大盘蓝筹，若市场风险偏好急剧下降或科技主线退潮，可能面临机构调仓抛压。",
        "score_factor_signal": {
          "selection_score_config_version": "main_theme_v2_2026_06_29",
          "ranked_weekly_theme_hit_count": 2,
          "weekly_theme_hit_count": 3,
          "reference_theme_hit_count": 5,
          "future_theme_hit_count": 0,
          "related_sub_theme_hit_count": 0,
          "resonance_label": "strong",
          "resonance_score": 2,
          "business_relevance_label": "core_business_related",
          "business_relevance_score": 1,
          "noise_label_list": [
            "none"
          ],
          "noise_score": 0,
          "reflection_risk_label_list": [
            "none"
          ],
          "reflection_risk_score": 0
        }
      },
      {
        "stock_code": "603738",
        "stock_name": "泰晶科技",
        "selection_score": 226,
        "matched_theme_list": [
          "半导体设备",
          "AI消费电子",
          "算力硬件",
          "CPO",
          "6G",
          "半导体",
          "人形机器人",
          "光通信"
        ],
        "matched_weekly_theme_list": [
          "半导体设备",
          "AI消费电子",
          "算力硬件"
        ],
        "matched_reference_theme_list": [
          "CPO",
          "6G",
          "半导体",
          "人形机器人",
          "光通信"
        ],
        "matched_future_theme_list": [],
        "resonance_type": "strong",
        "industry_chain_path": [
          "半导体光刻工艺",
          "石英频率元器件",
          "AI服务器/光通信/消费电子终端"
        ],
        "business_relevance_label": "core_business_related",
        "noise_label_list": [
          "none"
        ],
        "reflection_risk_label_list": [
          "none"
        ],
        "holding_style_label": "main_theme_trend",
        "reason_text": "公司主营石英晶体频率元器件，具备半导体光刻工艺技术，产品直接应用于光通信、AI、消费电子等领域，同时命中半导体设备、AI消费电子和算力硬件三大前排主线，产业链共振极强。",
        "risk_text": "作为上游被动元器件，若下游AI算力及消费电子需求复苏不及预期，可能面临订单波动风险。",
        "score_factor_signal": {
          "selection_score_config_version": "main_theme_v2_2026_06_29",
          "ranked_weekly_theme_hit_count": 2,
          "weekly_theme_hit_count": 3,
          "reference_theme_hit_count": 5,
          "future_theme_hit_count": 0,
          "related_sub_theme_hit_count": 0,
          "resonance_label": "strong",
          "resonance_score": 2,
          "business_relevance_label": "core_business_related",
          "business_relevance_score": 1,
          "noise_label_list": [
            "none"
          ],
          "noise_score": 0,
          "reflection_risk_label_list": [
            "none"
          ],
          "reflection_risk_score": 0
        }
      },
      {
        "stock_code": "002008",
        "stock_name": "大族激光",
        "selection_score": 216,
        "matched_theme_list": [
          "半导体设备",
          "AI消费电子",
          "算力硬件",
          "PCB",
          "光刻机"
        ],
        "matched_weekly_theme_list": [
          "半导体设备",
          "AI消费电子",
          "算力硬件"
        ],
        "matched_reference_theme_list": [
          "半导体",
          "PCB",
          "人形机器人",
          "AI"
        ],
        "matched_future_theme_list": [],
        "resonance_type": "strong",
        "industry_chain_path": [
          "半导体设备",
          "光刻机/激光加工",
          "PCB钻孔",
          "AI服务器/消费电子"
        ],
        "business_relevance_label": "core_business_related",
        "noise_label_list": [
          "none"
        ],
        "reflection_risk_label_list": [
          "none"
        ],
        "holding_style_label": "main_theme_trend",
        "reason_text": "公司主营激光加工设备及PCB钻孔机，是半导体设备和PCB上游核心装备，同时覆盖AI消费电子和算力硬件多条强相关主线，产业链路径清晰。",
        "risk_text": "若半导体及消费电子资本开支不及预期，设备端订单可能受影响。",
        "score_factor_signal": {
          "selection_score_config_version": "main_theme_v2_2026_06_29",
          "ranked_weekly_theme_hit_count": 2,
          "weekly_theme_hit_count": 3,
          "reference_theme_hit_count": 4,
          "future_theme_hit_count": 0,
          "related_sub_theme_hit_count": 1,
          "resonance_label": "strong",
          "resonance_score": 2,
          "business_relevance_label": "core_business_related",
          "business_relevance_score": 1,
          "noise_label_list": [
            "none"
          ],
          "noise_score": 0,
          "reflection_risk_label_list": [
            "none"
          ],
          "reflection_risk_score": 0
        }
      },
      {
        "stock_code": "002156",
        "stock_name": "通富微电",
        "selection_score": 211,
        "matched_theme_list": [
          "半导体设备",
          "AI消费电子",
          "算力硬件",
          "半导体",
          "CPO",
          "存储半导体",
          "PC"
        ],
        "matched_weekly_theme_list": [
          "半导体设备",
          "AI消费电子",
          "算力硬件"
        ],
        "matched_reference_theme_list": [
          "半导体",
          "CPO",
          "存储半导体",
          "PC"
        ],
        "matched_future_theme_list": [],
        "resonance_type": "strong",
        "industry_chain_path": [
          "半导体设备",
          "先进封装",
          "AI算力芯片",
          "AI PC"
        ],
        "business_relevance_label": "core_business_related",
        "noise_label_list": [
          "none"
        ],
        "reflection_risk_label_list": [
          "none"
        ],
        "holding_style_label": "main_theme_trend",
        "reason_text": "公司是本土半导体跨国企业，主营集成电路封装测试，同时获得国家大基金一期和二期投资。产品广泛应用于人工智能、高性能计算等领域，命中半导体设备、AI消费电子和算力硬件三大主线，产业链共振极强。",
        "risk_text": "若半导体行业周期复苏不及预期，或AI算力需求放缓，可能影响公司先进封装业务的产能利用率和盈利能力。",
        "score_factor_signal": {
          "selection_score_config_version": "main_theme_v2_2026_06_29",
          "ranked_weekly_theme_hit_count": 2,
          "weekly_theme_hit_count": 3,
          "reference_theme_hit_count": 4,
          "future_theme_hit_count": 0,
          "related_sub_theme_hit_count": 0,
          "resonance_label": "strong",
          "resonance_score": 2,
          "business_relevance_label": "core_business_related",
          "business_relevance_score": 1,
          "noise_label_list": [
            "none"
          ],
          "noise_score": 0,
          "reflection_risk_label_list": [
            "none"
          ],
          "reflection_risk_score": 0
        }
      },
      {
        "stock_code": "002886",
        "stock_name": "沃特股份",
        "selection_score": 209,
        "matched_theme_list": [
          "算力硬件",
          "AI消费电子",
          "半导体设备",
          "氟化工",
          "PCB",
          "先进封装"
        ],
        "matched_weekly_theme_list": [
          "算力硬件",
          "AI消费电子",
          "半导体设备",
          "氟化工"
        ],
        "matched_reference_theme_list": [
          "PCB",
          "半导体",
          "5G",
          "6G",
          "先进封装"
        ],
        "matched_future_theme_list": [],
        "resonance_type": "strong",
        "industry_chain_path": [
          "算力基建/CPO",
          "高频高速树脂/LCP",
          "含氟高分子"
        ],
        "business_relevance_label": "core_business_related",
        "noise_label_list": [
          "none"
        ],
        "reflection_risk_label_list": [
          "none"
        ],
        "holding_style_label": "main_theme_trend",
        "reason_text": "公司主营特种高分子材料，LCP等高频材料直接供应CPO/PCB及消费电子，含氟高分子材料契合氟化工主线，同时切入先进封装材料，产业链共振极强。",
        "risk_text": "新材料验证周期长，若下游算力与半导体客户导入不及预期，将影响业绩释放。",
        "score_factor_signal": {
          "selection_score_config_version": "main_theme_v2_2026_06_29",
          "ranked_weekly_theme_hit_count": 2,
          "weekly_theme_hit_count": 4,
          "reference_theme_hit_count": 3,
          "future_theme_hit_count": 0,
          "related_sub_theme_hit_count": 0,
          "resonance_label": "strong",
          "resonance_score": 2,
          "business_relevance_label": "core_business_related",
          "business_relevance_score": 1,
          "noise_label_list": [
            "none"
          ],
          "noise_score": 0,
          "reflection_risk_label_list": [
            "none"
          ],
          "reflection_risk_score": 0
        }
      },
      {
        "stock_code": "002049",
        "stock_name": "紫光国微",
        "selection_score": 206,
        "matched_theme_list": [
          "半导体设备",
          "AI消费电子",
          "算力硬件",
          "存储芯片",
          "特种集成电路"
        ],
        "matched_weekly_theme_list": [
          "半导体设备",
          "AI消费电子",
          "算力硬件"
        ],
        "matched_reference_theme_list": [
          "半导体",
          "存储半导体",
          "AI"
        ],
        "matched_future_theme_list": [],
        "resonance_type": "strong",
        "industry_chain_path": [
          "集成电路设计",
          "特种集成电路/存储芯片",
          "AI终端/算力服务器"
        ],
        "business_relevance_label": "core_business_related",
        "noise_label_list": [
          "none"
        ],
        "reflection_risk_label_list": [
          "none"
        ],
        "holding_style_label": "main_theme_trend",
        "reason_text": "国内集成电路设计龙头，主营特种集成电路、智能安全芯片和存储芯片，深度覆盖半导体、AI消费电子及算力硬件芯片需求，多主线强共振。",
        "risk_text": "特种集成电路需求受军工等下游影响，消费电子复苏节奏可能不及预期。",
        "score_factor_signal": {
          "selection_score_config_version": "main_theme_v2_2026_06_29",
          "ranked_weekly_theme_hit_count": 2,
          "weekly_theme_hit_count": 3,
          "reference_theme_hit_count": 3,
          "future_theme_hit_count": 0,
          "related_sub_theme_hit_count": 2,
          "resonance_label": "strong",
          "resonance_score": 2,
          "business_relevance_label": "core_business_related",
          "business_relevance_score": 1,
          "noise_label_list": [
            "none"
          ],
          "noise_score": 0,
          "reflection_risk_label_list": [
            "none"
          ],
          "reflection_risk_score": 0
        }
      },
      {
        "stock_code": "605589",
        "stock_name": "圣泉集团",
        "selection_score": 199,
        "matched_theme_list": [
          "半导体设备",
          "算力硬件",
          "创新药",
          "PCB",
          "覆铜板",
          "光刻胶"
        ],
        "matched_weekly_theme_list": [
          "半导体设备",
          "算力硬件",
          "创新药"
        ],
        "matched_reference_theme_list": [
          "PCB",
          "覆铜板",
          "光刻胶",
          "创新药",
          "半导体"
        ],
        "matched_future_theme_list": [],
        "resonance_type": "strong",
        "industry_chain_path": [
          "电子化学品/光刻胶",
          "半导体制造",
          "酚醛树脂/覆铜板",
          "PCB算力硬件",
          "合成生物/医药"
        ],
        "business_relevance_label": "core_business_related",
        "noise_label_list": [
          "concept_stacking"
        ],
        "reflection_risk_label_list": [
          "none"
        ],
        "holding_style_label": "main_theme_trend",
        "reason_text": "公司主营合成树脂及生物质新材料，酚醛树脂是PCB覆铜板核心材料，直接受益于算力硬件需求；同时布局半导体光刻胶及创新药/合成生物，多主线强共振且均有业务支撑。",
        "risk_text": "概念极其广泛，若主线轮动过快可能导致资金聚焦不足；部分新材料业务尚在培育期。",
        "score_factor_signal": {
          "selection_score_config_version": "main_theme_v2_2026_06_29",
          "ranked_weekly_theme_hit_count": 2,
          "weekly_theme_hit_count": 3,
          "reference_theme_hit_count": 4,
          "future_theme_hit_count": 0,
          "related_sub_theme_hit_count": 0,
          "resonance_label": "strong",
          "resonance_score": 2,
          "business_relevance_label": "core_business_related",
          "business_relevance_score": 1,
          "noise_label_list": [
            "concept_stacking"
          ],
          "noise_score": -1,
          "reflection_risk_label_list": [
            "none"
          ],
          "reflection_risk_score": 0
        }
      },
      {
        "stock_code": "603893",
        "stock_name": "瑞芯微",
        "selection_score": 198,
        "matched_theme_list": [
          "半导体设备",
          "AI消费电子",
          "半导体",
          "存储半导体",
          "AI",
          "人形机器人"
        ],
        "matched_weekly_theme_list": [
          "半导体设备",
          "AI消费电子"
        ],
        "matched_reference_theme_list": [
          "半导体",
          "存储半导体",
          "AI",
          "人形机器人"
        ],
        "matched_future_theme_list": [],
        "resonance_type": "strong",
        "industry_chain_path": [
          "半导体设计",
          "AIoT SoC",
          "AI终端硬件"
        ],
        "business_relevance_label": "core_business_related",
        "noise_label_list": [
          "none"
        ],
        "reflection_risk_label_list": [
          "none"
        ],
        "holding_style_label": "main_theme_trend",
        "reason_text": "公司主营智能应用处理器SoC，属于AI终端核心芯片，同时覆盖半导体设备和AI消费电子双主线，且有大基金持股概念，产业链逻辑极强。",
        "risk_text": "半导体周期复苏不及预期或AI终端渗透率提升放缓可能影响业绩释放。",
        "score_factor_signal": {
          "selection_score_config_version": "main_theme_v2_2026_06_29",
          "ranked_weekly_theme_hit_count": 2,
          "weekly_theme_hit_count": 2,
          "reference_theme_hit_count": 4,
          "future_theme_hit_count": 0,
          "related_sub_theme_hit_count": 0,
          "resonance_label": "strong",
          "resonance_score": 2,
          "business_relevance_label": "core_business_related",
          "business_relevance_score": 1,
          "noise_label_list": [
            "none"
          ],
          "noise_score": 0,
          "reflection_risk_label_list": [
            "none"
          ],
          "reflection_risk_score": 0
        }
      },
      {
        "stock_code": "603203",
        "stock_name": "快克智能",
        "selection_score": 196,
        "matched_theme_list": [
          "半导体设备",
          "算力硬件",
          "AI消费电子"
        ],
        "matched_weekly_theme_list": [
          "半导体设备",
          "算力硬件",
          "AI消费电子"
        ],
        "matched_reference_theme_list": [
          "CPO",
          "PCB",
          "半导体"
        ],
        "matched_future_theme_list": [],
        "resonance_type": "strong",
        "industry_chain_path": [
          "半导体封装/CPO组装/消费电子组装",
          "智能装备"
        ],
        "business_relevance_label": "core_business_related",
        "noise_label_list": [
          "none"
        ],
        "reflection_risk_label_list": [
          "none"
        ],
        "holding_style_label": "main_theme_trend",
        "reason_text": "公司提供半导体封装检测和精密电子组装智能装备，同时命中半导体设备、算力硬件和AI消费电子三大主线，设备端强共振。",
        "risk_text": "设备订单交付周期较长，若下游资本开支放缓，可能影响业绩释放节奏。",
        "score_factor_signal": {
          "selection_score_config_version": "main_theme_v2_2026_06_29",
          "ranked_weekly_theme_hit_count": 2,
          "weekly_theme_hit_count": 3,
          "reference_theme_hit_count": 3,
          "future_theme_hit_count": 0,
          "related_sub_theme_hit_count": 0,
          "resonance_label": "strong",
          "resonance_score": 2,
          "business_relevance_label": "core_business_related",
          "business_relevance_score": 1,
          "noise_label_list": [
            "none"
          ],
          "noise_score": 0,
          "reflection_risk_label_list": [
            "none"
          ],
          "reflection_risk_score": 0
        }
      },
      {
        "stock_code": "003031",
        "stock_name": "中瓷电子",
        "selection_score": 190,
        "matched_theme_list": [
          "算力硬件",
          "半导体设备",
          "AI消费电子",
          "CPO",
          "光刻机",
          "消费电子概念"
        ],
        "matched_weekly_theme_list": [
          "算力硬件",
          "半导体设备",
          "AI消费电子"
        ],
        "matched_reference_theme_list": [
          "CPO",
          "半导体"
        ],
        "matched_future_theme_list": [],
        "resonance_type": "strong",
        "industry_chain_path": [
          "算力基建",
          "CPO陶瓷外壳",
          "第三代半导体器件",
          "AI终端消费电子"
        ],
        "business_relevance_label": "core_business_related",
        "noise_label_list": [
          "none"
        ],
        "reflection_risk_label_list": [
          "none"
        ],
        "holding_style_label": "main_theme_trend",
        "reason_text": "公司主营电子陶瓷外壳及第三代半导体，光通信器件外壳直接受益于算力CPO方向，同时半导体器件及消费电子业务覆盖周级多条强主线，产业链共振极强。",
        "risk_text": "CPO及半导体方向若出现资金退潮，公司作为高弹性标的可能面临较大波动。",
        "score_factor_signal": {
          "selection_score_config_version": "main_theme_v2_2026_06_29",
          "ranked_weekly_theme_hit_count": 2,
          "weekly_theme_hit_count": 3,
          "reference_theme_hit_count": 2,
          "future_theme_hit_count": 0,
          "related_sub_theme_hit_count": 2,
          "resonance_label": "strong",
          "resonance_score": 2,
          "business_relevance_label": "core_business_related",
          "business_relevance_score": 1,
          "noise_label_list": [
            "none"
          ],
          "noise_score": 0,
          "reflection_risk_label_list": [
            "none"
          ],
          "reflection_risk_score": 0
        }
      },
      {
        "stock_code": "002475",
        "stock_name": "立讯精密",
        "selection_score": 189,
        "matched_theme_list": [
          "AI消费电子",
          "算力硬件",
          "铜缆高速连接",
          "CPO"
        ],
        "matched_weekly_theme_list": [
          "AI消费电子",
          "算力硬件"
        ],
        "matched_reference_theme_list": [
          "CPO",
          "人形机器人",
          "AI",
          "PC",
          "6G"
        ],
        "matched_future_theme_list": [],
        "resonance_type": "strong",
        "industry_chain_path": [
          "AI终端",
          "消费电子组装/连接",
          "算力基建铜连接/CPO"
        ],
        "business_relevance_label": "core_business_related",
        "noise_label_list": [
          "none"
        ],
        "reflection_risk_label_list": [
          "none"
        ],
        "holding_style_label": "main_theme_trend",
        "reason_text": "公司是消费电子及连接器龙头，主营深度覆盖AI消费电子及算力硬件的铜缆高速连接与CPO，产业链共振极强。",
        "risk_text": "消费电子复苏不及预期或算力基建需求放缓可能影响业绩。",
        "score_factor_signal": {
          "selection_score_config_version": "main_theme_v2_2026_06_29",
          "ranked_weekly_theme_hit_count": 1,
          "weekly_theme_hit_count": 2,
          "reference_theme_hit_count": 5,
          "future_theme_hit_count": 0,
          "related_sub_theme_hit_count": 1,
          "resonance_label": "strong",
          "resonance_score": 2,
          "business_relevance_label": "core_business_related",
          "business_relevance_score": 1,
          "noise_label_list": [
            "none"
          ],
          "noise_score": 0,
          "reflection_risk_label_list": [
            "none"
          ],
          "reflection_risk_score": 0
        }
      },
      {
        "stock_code": "605358",
        "stock_name": "立昂微",
        "selection_score": 184,
        "matched_theme_list": [
          "半导体设备",
          "AI消费电子",
          "算力硬件",
          "半导体",
          "CPO"
        ],
        "matched_weekly_theme_list": [
          "半导体设备",
          "AI消费电子",
          "算力硬件"
        ],
        "matched_reference_theme_list": [
          "半导体",
          "CPO",
          "存储半导体",
          "5G"
        ],
        "matched_future_theme_list": [],
        "resonance_type": "strong",
        "industry_chain_path": [
          "半导体硅片",
          "芯片制造",
          "AI算力/消费电子芯片"
        ],
        "business_relevance_label": "core_business_related",
        "noise_label_list": [
          "concept_stacking"
        ],
        "reflection_risk_label_list": [
          "none"
        ],
        "holding_style_label": "main_theme_trend",
        "reason_text": "公司主营半导体硅片和分立器件芯片，是半导体产业链上游核心材料，直接受益于半导体设备主线；同时产品广泛应用于5G、汽车电子等领域，与AI消费电子及算力硬件产生强共振。",
        "risk_text": "半导体周期复苏不及预期风险；概念标签过多，部分边缘概念可能分散资金注意力。",
        "score_factor_signal": {
          "selection_score_config_version": "main_theme_v2_2026_06_29",
          "ranked_weekly_theme_hit_count": 2,
          "weekly_theme_hit_count": 3,
          "reference_theme_hit_count": 3,
          "future_theme_hit_count": 0,
          "related_sub_theme_hit_count": 0,
          "resonance_label": "strong",
          "resonance_score": 2,
          "business_relevance_label": "core_business_related",
          "business_relevance_score": 1,
          "noise_label_list": [
            "concept_stacking"
          ],
          "noise_score": -1,
          "reflection_risk_label_list": [
            "none"
          ],
          "reflection_risk_score": 0
        }
      },
      {
        "stock_code": "603501",
        "stock_name": "豪威集团",
        "selection_score": 183,
        "matched_theme_list": [
          "半导体设备",
          "AI消费电子"
        ],
        "matched_weekly_theme_list": [
          "半导体设备",
          "AI消费电子"
        ],
        "matched_reference_theme_list": [
          "半导体",
          "AI",
          "PC"
        ],
        "matched_future_theme_list": [],
        "resonance_type": "strong",
        "industry_chain_path": [
          "半导体设计",
          "图像传感器",
          "AI手机/AI PC"
        ],
        "business_relevance_label": "core_business_related",
        "noise_label_list": [
          "none"
        ],
        "reflection_risk_label_list": [
          "none"
        ],
        "holding_style_label": "main_theme_trend",
        "reason_text": "公司主营图像传感器芯片，属于半导体设计核心环节，且产品直接应用于AI手机、AI PC等消费电子领域，同时命中半导体设备和AI消费电子两大主线，产业链共振极强。",
        "risk_text": "消费电子复苏不及预期可能影响图像传感器需求；半导体周期波动风险。",
        "score_factor_signal": {
          "selection_score_config_version": "main_theme_v2_2026_06_29",
          "ranked_weekly_theme_hit_count": 2,
          "weekly_theme_hit_count": 2,
          "reference_theme_hit_count": 3,
          "future_theme_hit_count": 0,
          "related_sub_theme_hit_count": 0,
          "resonance_label": "strong",
          "resonance_score": 2,
          "business_relevance_label": "core_business_related",
          "business_relevance_score": 1,
          "noise_label_list": [
            "none"
          ],
          "noise_score": 0,
          "reflection_risk_label_list": [
            "none"
          ],
          "reflection_risk_score": 0
        }
      },
      {
        "stock_code": "000021",
        "stock_name": "深科技",
        "selection_score": 180,
        "matched_theme_list": [
          "算力硬件",
          "AI消费电子",
          "半导体设备",
          "CPO",
          "存储半导体"
        ],
        "matched_weekly_theme_list": [
          "算力硬件",
          "AI消费电子",
          "半导体设备"
        ],
        "matched_reference_theme_list": [
          "CPO",
          "存储半导体"
        ],
        "matched_future_theme_list": [],
        "resonance_type": "strong",
        "industry_chain_path": [
          "AI服务器",
          "存储芯片",
          "CPO",
          "消费电子制造"
        ],
        "business_relevance_label": "core_business_related",
        "noise_label_list": [
          "none"
        ],
        "reflection_risk_label_list": [
          "none"
        ],
        "holding_style_label": "main_theme_trend",
        "reason_text": "公司聚焦存储半导体和高端制造，内存条及U盘业务受益于存算一体需求，CPO和消费电子制造与算力硬件及AI终端主线共振强烈。",
        "risk_text": "存储周期波动可能影响业绩弹性，CPO业务占比需跟踪确认。",
        "score_factor_signal": {
          "selection_score_config_version": "main_theme_v2_2026_06_29",
          "ranked_weekly_theme_hit_count": 2,
          "weekly_theme_hit_count": 3,
          "reference_theme_hit_count": 2,
          "future_theme_hit_count": 0,
          "related_sub_theme_hit_count": 0,
          "resonance_label": "strong",
          "resonance_score": 2,
          "business_relevance_label": "core_business_related",
          "business_relevance_score": 1,
          "noise_label_list": [
            "none"
          ],
          "noise_score": 0,
          "reflection_risk_label_list": [
            "none"
          ],
          "reflection_risk_score": 0
        }
      },
      {
        "stock_code": "002859",
        "stock_name": "洁美科技",
        "selection_score": 180,
        "matched_theme_list": [
          "算力硬件",
          "半导体设备",
          "AI消费电子",
          "PCB"
        ],
        "matched_weekly_theme_list": [
          "算力硬件",
          "半导体设备",
          "AI消费电子"
        ],
        "matched_reference_theme_list": [
          "PCB",
          "半导体"
        ],
        "matched_future_theme_list": [],
        "resonance_type": "strong",
        "industry_chain_path": [
          "半导体/PCB",
          "电子封装材料/离型膜"
        ],
        "business_relevance_label": "core_business_related",
        "noise_label_list": [
          "none"
        ],
        "reflection_risk_label_list": [
          "none"
        ],
        "holding_style_label": "main_theme_trend",
        "reason_text": "公司主营电子元器件载带及离型膜，是半导体与PCB上游核心耗材，直接受益于算力硬件扩产与AI终端消费电子需求拉动。",
        "risk_text": "下游半导体周期波动可能影响耗材需求，离型膜国产替代进程若放缓将影响增速。",
        "score_factor_signal": {
          "selection_score_config_version": "main_theme_v2_2026_06_29",
          "ranked_weekly_theme_hit_count": 2,
          "weekly_theme_hit_count": 3,
          "reference_theme_hit_count": 2,
          "future_theme_hit_count": 0,
          "related_sub_theme_hit_count": 0,
          "resonance_label": "strong",
          "resonance_score": 2,
          "business_relevance_label": "core_business_related",
          "business_relevance_score": 1,
          "noise_label_list": [
            "none"
          ],
          "noise_score": 0,
          "reflection_risk_label_list": [
            "none"
          ],
          "reflection_risk_score": 0
        }
      },
      {
        "stock_code": "600703",
        "stock_name": "三安光电",
        "selection_score": 180,
        "matched_theme_list": [
          "半导体设备",
          "AI消费电子",
          "算力硬件",
          "CPO",
          "半导体"
        ],
        "matched_weekly_theme_list": [
          "半导体设备",
          "AI消费电子",
          "算力硬件"
        ],
        "matched_reference_theme_list": [
          "CPO",
          "半导体"
        ],
        "matched_future_theme_list": [],
        "resonance_type": "strong",
        "industry_chain_path": [
          "半导体材料",
          "化合物芯片",
          "CPO/光通信",
          "AI终端"
        ],
        "business_relevance_label": "core_business_related",
        "noise_label_list": [
          "none"
        ],
        "reflection_risk_label_list": [
          "none"
        ],
        "holding_style_label": "main_theme_trend",
        "reason_text": "化合物半导体龙头，业务覆盖CPO光技术、Mini/MicroLED及消费电子芯片，同时命中半导体设备、AI消费电子和算力硬件三大主线，产业链共振极强。",
        "risk_text": "半导体周期复苏不及预期，CPO及消费电子需求可能波动。",
        "score_factor_signal": {
          "selection_score_config_version": "main_theme_v2_2026_06_29",
          "ranked_weekly_theme_hit_count": 2,
          "weekly_theme_hit_count": 3,
          "reference_theme_hit_count": 2,
          "future_theme_hit_count": 0,
          "related_sub_theme_hit_count": 0,
          "resonance_label": "strong",
          "resonance_score": 2,
          "business_relevance_label": "core_business_related",
          "business_relevance_score": 1,
          "noise_label_list": [
            "none"
          ],
          "noise_score": 0,
          "reflection_risk_label_list": [
            "none"
          ],
          "reflection_risk_score": 0
        }
      },
      {
        "stock_code": "601208",
        "stock_name": "东材科技",
        "selection_score": 180,
        "matched_theme_list": [
          "算力硬件",
          "AI消费电子",
          "半导体设备",
          "PCB",
          "覆铜板"
        ],
        "matched_weekly_theme_list": [
          "算力硬件",
          "AI消费电子",
          "半导体设备"
        ],
        "matched_reference_theme_list": [
          "PCB",
          "覆铜板",
          "消费电子概念"
        ],
        "matched_future_theme_list": [],
        "resonance_type": "strong",
        "industry_chain_path": [
          "AI算力/消费电子",
          "PCB/覆铜板",
          "电子级树脂/光学膜材料"
        ],
        "business_relevance_label": "core_business_related",
        "noise_label_list": [
          "none"
        ],
        "reflection_risk_label_list": [
          "none"
        ],
        "holding_style_label": "main_theme_trend",
        "reason_text": "公司主营电子级树脂材料和光学膜，是PCB覆铜板和消费电子的核心上游材料，同时切入光刻胶领域，多主线强共振且业务支撑极强。",
        "risk_text": "化工新材料产能释放不及预期，或下游消费电子需求复苏缓慢可能拖累业绩。",
        "score_factor_signal": {
          "selection_score_config_version": "main_theme_v2_2026_06_29",
          "ranked_weekly_theme_hit_count": 2,
          "weekly_theme_hit_count": 3,
          "reference_theme_hit_count": 2,
          "future_theme_hit_count": 0,
          "related_sub_theme_hit_count": 0,
          "resonance_label": "strong",
          "resonance_score": 2,
          "business_relevance_label": "core_business_related",
          "business_relevance_score": 1,
          "noise_label_list": [
            "none"
          ],
          "noise_score": 0,
          "reflection_risk_label_list": [
            "none"
          ],
          "reflection_risk_score": 0
        }
      },
      {
        "stock_code": "603005",
        "stock_name": "晶方科技",
        "selection_score": 177,
        "matched_theme_list": [
          "半导体设备",
          "AI消费电子",
          "先进封装",
          "传感器"
        ],
        "matched_weekly_theme_list": [
          "半导体设备",
          "AI消费电子"
        ],
        "matched_reference_theme_list": [
          "半导体",
          "存储半导体"
        ],
        "matched_future_theme_list": [],
        "resonance_type": "strong",
        "industry_chain_path": [
          "AI终端",
          "消费电子",
          "传感器封装",
          "先进封装"
        ],
        "business_relevance_label": "core_business_related",
        "noise_label_list": [
          "none"
        ],
        "reflection_risk_label_list": [
          "none"
        ],
        "holding_style_label": "main_theme_trend",
        "reason_text": "公司主营传感器封装测试，拥有晶圆级先进封装技术，同时命中半导体设备与AI消费电子两大主线，产业链路径真实。",
        "risk_text": "消费电子复苏不及预期可能影响封装需求，先进封装技术迭代竞争加剧。",
        "score_factor_signal": {
          "selection_score_config_version": "main_theme_v2_2026_06_29",
          "ranked_weekly_theme_hit_count": 2,
          "weekly_theme_hit_count": 2,
          "reference_theme_hit_count": 2,
          "future_theme_hit_count": 0,
          "related_sub_theme_hit_count": 2,
          "resonance_label": "strong",
          "resonance_score": 2,
          "business_relevance_label": "core_business_related",
          "business_relevance_score": 1,
          "noise_label_list": [
            "none"
          ],
          "noise_score": 0,
          "reflection_risk_label_list": [
            "none"
          ],
          "reflection_risk_score": 0
        }
      },
      {
        "stock_code": "002273",
        "stock_name": "水晶光电",
        "selection_score": 174,
        "matched_theme_list": [
          "AI消费电子",
          "算力硬件",
          "CPO",
          "AI手机"
        ],
        "matched_weekly_theme_list": [
          "AI消费电子",
          "算力硬件"
        ],
        "matched_reference_theme_list": [
          "CPO",
          "PC",
          "人形机器人",
          "AI"
        ],
        "matched_future_theme_list": [],
        "resonance_type": "strong",
        "industry_chain_path": [
          "AI手机/消费电子",
          "光学元器件",
          "CPO"
        ],
        "business_relevance_label": "core_business_related",
        "noise_label_list": [
          "none"
        ],
        "reflection_risk_label_list": [
          "none"
        ],
        "holding_style_label": "main_theme_trend",
        "reason_text": "公司主营光学光电子元器件，是AI手机和消费电子核心组件供应商，同时布局CPO，与本周AI消费电子和算力硬件双主线强共振。",
        "risk_text": "消费电子复苏不及预期可能影响业绩，CPO技术路线变化带来不确定性。",
        "score_factor_signal": {
          "selection_score_config_version": "main_theme_v2_2026_06_29",
          "ranked_weekly_theme_hit_count": 1,
          "weekly_theme_hit_count": 2,
          "reference_theme_hit_count": 4,
          "future_theme_hit_count": 0,
          "related_sub_theme_hit_count": 1,
          "resonance_label": "strong",
          "resonance_score": 2,
          "business_relevance_label": "core_business_related",
          "business_relevance_score": 1,
          "noise_label_list": [
            "none"
          ],
          "noise_score": 0,
          "reflection_risk_label_list": [
            "none"
          ],
          "reflection_risk_score": 0
        }
      },
      {
        "stock_code": "601609",
        "stock_name": "金田股份",
        "selection_score": 174,
        "matched_theme_list": [
          "算力硬件",
          "AI消费电子",
          "人形机器人",
          "铜缆高速连接"
        ],
        "matched_weekly_theme_list": [
          "算力硬件",
          "AI消费电子"
        ],
        "matched_reference_theme_list": [
          "人形机器人",
          "CPO",
          "算力租赁",
          "AI"
        ],
        "matched_future_theme_list": [],
        "resonance_type": "strong",
        "industry_chain_path": [
          "AI算力",
          "液冷服务器",
          "铜缆高速连接",
          "铜加工"
        ],
        "business_relevance_label": "core_business_related",
        "noise_label_list": [
          "none"
        ],
        "reflection_risk_label_list": [
          "none"
        ],
        "holding_style_label": "main_theme_trend",
        "reason_text": "公司主营铜产品及先进材料制造，明确提及为AI算力、人形机器人提供材料解决方案，铜缆高速连接是算力硬件核心，产业链共振强。",
        "risk_text": "概念标签较多，若算力硬件及机器人主线退潮，可能面临杀估值风险。",
        "score_factor_signal": {
          "selection_score_config_version": "main_theme_v2_2026_06_29",
          "ranked_weekly_theme_hit_count": 1,
          "weekly_theme_hit_count": 2,
          "reference_theme_hit_count": 4,
          "future_theme_hit_count": 0,
          "related_sub_theme_hit_count": 1,
          "resonance_label": "strong",
          "resonance_score": 2,
          "business_relevance_label": "core_business_related",
          "business_relevance_score": 1,
          "noise_label_list": [
            "none"
          ],
          "noise_score": 0,
          "reflection_risk_label_list": [
            "none"
          ],
          "reflection_risk_score": 0
        }
      },
      {
        "stock_code": "002057",
        "stock_name": "中钢天源",
        "selection_score": 170,
        "matched_theme_list": [
          "半导体设备",
          "AI消费电子",
          "小金属",
          "软磁材料"
        ],
        "matched_weekly_theme_list": [
          "半导体设备",
          "AI消费电子"
        ],
        "matched_reference_theme_list": [
          "小金属",
          "人形机器人",
          "机器人"
        ],
        "matched_future_theme_list": [],
        "resonance_type": "medium",
        "industry_chain_path": [
          "电子级四氧化三锰/软磁粉末",
          "磁性器件",
          "半导体/消费电子/机器人电机"
        ],
        "business_relevance_label": "core_business_related",
        "noise_label_list": [
          "none"
        ],
        "reflection_risk_label_list": [
          "none"
        ],
        "holding_style_label": "observe_only",
        "reason_text": "公司生产电子级四氧化三锰和铁基软磁粉末，是半导体和消费电子及机器人电机的上游核心材料，业务支撑较强。",
        "risk_text": "小金属和磁性材料价格波动大，下游需求受整体电子周期影响。",
        "score_factor_signal": {
          "selection_score_config_version": "main_theme_v2_2026_06_29",
          "ranked_weekly_theme_hit_count": 2,
          "weekly_theme_hit_count": 2,
          "reference_theme_hit_count": 3,
          "future_theme_hit_count": 0,
          "related_sub_theme_hit_count": 1,
          "resonance_label": "medium",
          "resonance_score": 1,
          "business_relevance_label": "core_business_related",
          "business_relevance_score": 1,
          "noise_label_list": [
            "none"
          ],
          "noise_score": 0,
          "reflection_risk_label_list": [
            "none"
          ],
          "reflection_risk_score": 0
        }
      },
      {
        "stock_code": "001389",
        "stock_name": "广合科技",
        "selection_score": 169,
        "matched_theme_list": [
          "算力硬件",
          "AI消费电子",
          "PCB",
          "CPO",
          "AI",
          "PC"
        ],
        "matched_weekly_theme_list": [
          "算力硬件",
          "AI消费电子"
        ],
        "matched_reference_theme_list": [
          "PCB",
          "CPO",
          "AI",
          "PC"
        ],
        "matched_future_theme_list": [],
        "resonance_type": "strong",
        "industry_chain_path": [
          "算力基建",
          "高速PCB",
          "数据中心",
          "AI服务器"
        ],
        "business_relevance_label": "core_business_related",
        "noise_label_list": [
          "none"
        ],
        "reflection_risk_label_list": [
          "none"
        ],
        "holding_style_label": "main_theme_trend",
        "reason_text": "公司主营高端PCB，产品直接应用于数据中心、云计算和人工智能领域，同时命中算力硬件与AI消费电子两大周级主线，且与CPO、PCB等多个参考主题重合，产业链路径清晰，主营业务强支撑。",
        "risk_text": "算力硬件需求若不及预期，可能导致PCB订单下滑；同时面临行业竞争加剧风险。",
        "score_factor_signal": {
          "selection_score_config_version": "main_theme_v2_2026_06_29",
          "ranked_weekly_theme_hit_count": 1,
          "weekly_theme_hit_count": 2,
          "reference_theme_hit_count": 4,
          "future_theme_hit_count": 0,
          "related_sub_theme_hit_count": 0,
          "resonance_label": "strong",
          "resonance_score": 2,
          "business_relevance_label": "core_business_related",
          "business_relevance_score": 1,
          "noise_label_list": [
            "none"
          ],
          "noise_score": 0,
          "reflection_risk_label_list": [
            "none"
          ],
          "reflection_risk_score": 0
        }
      },
      {
        "stock_code": "002384",
        "stock_name": "东山精密",
        "selection_score": 169,
        "matched_theme_list": [
          "AI消费电子",
          "算力硬件"
        ],
        "matched_weekly_theme_list": [
          "AI消费电子",
          "算力硬件"
        ],
        "matched_reference_theme_list": [
          "CPO",
          "PCB",
          "AI",
          "PC"
        ],
        "matched_future_theme_list": [],
        "resonance_type": "strong",
        "industry_chain_path": [
          "AI服务器",
          "高速PCB/CPO",
          "AI手机终端"
        ],
        "business_relevance_label": "core_business_related",
        "noise_label_list": [
          "none"
        ],
        "reflection_risk_label_list": [
          "none"
        ],
        "holding_style_label": "main_theme_trend",
        "reason_text": "公司是PCB及消费电子核心标的，深度受益于AI算力基建(CPO/PCB)及AI手机换机周期，多主线强共振。",
        "risk_text": "消费电子需求复苏不及预期；算力硬件竞争加剧及毛利率波动。",
        "score_factor_signal": {
          "selection_score_config_version": "main_theme_v2_2026_06_29",
          "ranked_weekly_theme_hit_count": 1,
          "weekly_theme_hit_count": 2,
          "reference_theme_hit_count": 4,
          "future_theme_hit_count": 0,
          "related_sub_theme_hit_count": 0,
          "resonance_label": "strong",
          "resonance_score": 2,
          "business_relevance_label": "core_business_related",
          "business_relevance_score": 1,
          "noise_label_list": [
            "none"
          ],
          "noise_score": 0,
          "reflection_risk_label_list": [
            "none"
          ],
          "reflection_risk_score": 0
        }
      },
      {
        "stock_code": "002579",
        "stock_name": "中京电子",
        "selection_score": 169,
        "matched_theme_list": [
          "AI消费电子",
          "算力硬件",
          "PCB",
          "AI PC",
          "AI手机",
          "CPO"
        ],
        "matched_weekly_theme_list": [
          "AI消费电子",
          "算力硬件"
        ],
        "matched_reference_theme_list": [
          "PCB",
          "pcb",
          "AI PC",
          "AI手机",
          "CPO",
          "6G"
        ],
        "matched_future_theme_list": [],
        "resonance_type": "strong",
        "industry_chain_path": [
          "AI终端/手机/PC",
          "PCB/FPC",
          "算力基建CPO"
        ],
        "business_relevance_label": "core_business_related",
        "noise_label_list": [
          "none"
        ],
        "reflection_risk_label_list": [
          "none"
        ],
        "holding_style_label": "main_theme_trend",
        "reason_text": "公司主营PCB及FPC，产品深度覆盖AI手机、AI PC及CPO等算力硬件核心环节，多主线强共振。",
        "risk_text": "PCB行业竞争激烈，若消费电子及算力需求不及预期，可能面临量价压力。",
        "score_factor_signal": {
          "selection_score_config_version": "main_theme_v2_2026_06_29",
          "ranked_weekly_theme_hit_count": 1,
          "weekly_theme_hit_count": 2,
          "reference_theme_hit_count": 4,
          "future_theme_hit_count": 0,
          "related_sub_theme_hit_count": 0,
          "resonance_label": "strong",
          "resonance_score": 2,
          "business_relevance_label": "core_business_related",
          "business_relevance_score": 1,
          "noise_label_list": [
            "none"
          ],
          "noise_score": 0,
          "reflection_risk_label_list": [
            "none"
          ],
          "reflection_risk_score": 0
        }
      },
      {
        "stock_code": "002938",
        "stock_name": "鹏鼎控股",
        "selection_score": 169,
        "matched_theme_list": [
          "算力硬件",
          "AI消费电子",
          "PCB",
          "CPO",
          "AI",
          "PC"
        ],
        "matched_weekly_theme_list": [
          "算力硬件",
          "AI消费电子"
        ],
        "matched_reference_theme_list": [
          "PCB",
          "CPO",
          "AI",
          "PC"
        ],
        "matched_future_theme_list": [],
        "resonance_type": "strong",
        "industry_chain_path": [
          "AI服务器/AI终端",
          "PCB制造"
        ],
        "business_relevance_label": "core_business_related",
        "noise_label_list": [
          "none"
        ],
        "reflection_risk_label_list": [
          "none"
        ],
        "holding_style_label": "main_theme_trend",
        "reason_text": "全球PCB龙头，主营各类印制电路板，同时命中算力硬件与AI消费电子双主线，且与PCB、CPO等参考主题强共振，产业链路径清晰，主营业务完全支撑。",
        "risk_text": "消费电子复苏不及预期可能影响产能利用率和业绩。",
        "score_factor_signal": {
          "selection_score_config_version": "main_theme_v2_2026_06_29",
          "ranked_weekly_theme_hit_count": 1,
          "weekly_theme_hit_count": 2,
          "reference_theme_hit_count": 4,
          "future_theme_hit_count": 0,
          "related_sub_theme_hit_count": 0,
          "resonance_label": "strong",
          "resonance_score": 2,
          "business_relevance_label": "core_business_related",
          "business_relevance_score": 1,
          "noise_label_list": [
            "none"
          ],
          "noise_score": 0,
          "reflection_risk_label_list": [
            "none"
          ],
          "reflection_risk_score": 0
        }
      },
      {
        "stock_code": "601138",
        "stock_name": "工业富联",
        "selection_score": 169,
        "matched_theme_list": [
          "算力硬件",
          "AI消费电子",
          "CPO",
          "算力租赁"
        ],
        "matched_weekly_theme_list": [
          "算力硬件",
          "AI消费电子"
        ],
        "matched_reference_theme_list": [
          "CPO",
          "算力租赁",
          "AI",
          "光通信"
        ],
        "matched_future_theme_list": [],
        "resonance_type": "strong",
        "industry_chain_path": [
          "AI算力",
          "AI服务器",
          "云服务设备",
          "CPO/液冷"
        ],
        "business_relevance_label": "core_business_related",
        "noise_label_list": [
          "none"
        ],
        "reflection_risk_label_list": [
          "none"
        ],
        "holding_style_label": "main_theme_trend",
        "reason_text": "全球领先的AI服务器和云服务设备制造商，直接受益于算力硬件需求爆发，CPO和液冷技术布局领先，产业链核心标的。",
        "risk_text": "全球AI资本开支增速放缓风险，以及地缘政治对供应链的潜在冲击。",
        "score_factor_signal": {
          "selection_score_config_version": "main_theme_v2_2026_06_29",
          "ranked_weekly_theme_hit_count": 1,
          "weekly_theme_hit_count": 2,
          "reference_theme_hit_count": 4,
          "future_theme_hit_count": 0,
          "related_sub_theme_hit_count": 0,
          "resonance_label": "strong",
          "resonance_score": 2,
          "business_relevance_label": "core_business_related",
          "business_relevance_score": 1,
          "noise_label_list": [
            "none"
          ],
          "noise_score": 0,
          "reflection_risk_label_list": [
            "none"
          ],
          "reflection_risk_score": 0
        }
      },
      {
        "stock_code": "603228",
        "stock_name": "景旺电子",
        "selection_score": 169,
        "matched_theme_list": [
          "算力硬件",
          "AI消费电子"
        ],
        "matched_weekly_theme_list": [
          "算力硬件",
          "AI消费电子"
        ],
        "matched_reference_theme_list": [
          "PCB",
          "CPO",
          "AI",
          "PC"
        ],
        "matched_future_theme_list": [],
        "resonance_type": "strong",
        "industry_chain_path": [
          "AI服务器/AI PC",
          "高频高速PCB",
          "景旺电子"
        ],
        "business_relevance_label": "core_business_related",
        "noise_label_list": [
          "none"
        ],
        "reflection_risk_label_list": [
          "none"
        ],
        "holding_style_label": "main_theme_trend",
        "reason_text": "公司是PCB行业龙头，产品覆盖CPO、AI PC等方向，同时命中算力硬件和AI消费电子主线，产业链逻辑极强。",
        "risk_text": "PCB行业周期性较强，若AI终端换机周期延后，可能影响高端PCB放量。",
        "score_factor_signal": {
          "selection_score_config_version": "main_theme_v2_2026_06_29",
          "ranked_weekly_theme_hit_count": 1,
          "weekly_theme_hit_count": 2,
          "reference_theme_hit_count": 4,
          "future_theme_hit_count": 0,
          "related_sub_theme_hit_count": 0,
          "resonance_label": "strong",
          "resonance_score": 2,
          "business_relevance_label": "core_business_related",
          "business_relevance_score": 1,
          "noise_label_list": [
            "none"
          ],
          "noise_score": 0,
          "reflection_risk_label_list": [
            "none"
          ],
          "reflection_risk_score": 0
        }
      }
    ],
    "summary_text": "分批主线候选召回完成，已按程序计算的 selection_score 合并排序并保留最终候选池。",
    "published_source_date": "2026-07-01"
  }
}